README.md
pyproject.toml
heatmap_greatseal/__init__.py
heatmap_greatseal/heatmap_greatseal.py
heatmap_greatseal.egg-info/PKG-INFO
heatmap_greatseal.egg-info/SOURCES.txt
heatmap_greatseal.egg-info/dependency_links.txt
heatmap_greatseal.egg-info/requires.txt
heatmap_greatseal.egg-info/top_level.txt
tests/test_add.py
tests/test_neighbour.py
tests/test_rotate.py
tests/test_substract.py